{"gTzXGSMgt3iMfH2VZglKVQ==":"mbr-2000x1336.jpg","EBkqk6zGw962CcLEaM6PSA==":"mbr-2000x1333.jpg","1V337yMDz+l1pC/W8TGj4w==":"roberto-2000x1324.jpg","D/IHmLNku2/4D7sDKUeqgw==":"el%20molinon-600x320.jpg","Cr1xJA0bysq4XbobDMrNmA==":"el%20pe%C3%B1agrande-600x261.jpg","0oGMuDgVOlj/+dc50Kjozg==":"la%20casilla-600x400.jpg","RnMEHB7Qo1Vl86WnmP9NrQ==":"hotel%20ana-600x399.jpg","4OVH0ugUoarRaQj4d1VJCQ==":"la%20casilla%202-2000x1170.jpg","+lJ0t1/1wDeCKp1Ap8EFig==":"la%20casilla%203-2000x1231.jpg","LsY3Hgspf/RYc9n0SgH8Og==":"la%20casilla%20habitacion%201-2000x1331.jpg","DkQ1OjAiYqXWtBmBFTUzfw==":"la%20casilla%20habitacion%202-2000x1170.jpg","MR+boWzd8lyi6QuDiA6hrg==":"la%20casilla%203-2000x1232.jpg","WuYLW9B8u6K8GXzSknstPQ==":"el%20molinon-600x319.jpg","3IMClcS/gcSwKPuAapZLsw==":"el%20molinon-600x319.jpg","KS/IfwLMCAd5nvS++wBJzA==":"mbr-600x400.jpg","fEGUwE3zF+Q9LgpZVaONEw==":"mbr-1-600x400.jpg","jxNIKMwXo/tz86ler6EDRg==":"el%20molinon-600x319.jpg","+ScwRhTHe8mMAFe6Fblu8w==":"molinon%20habitacion%201-2000x1066.jpg","NMB17ct1+SCPdEv9IZNGOQ==":"molinon%20habitacion%202-2000x1066.jpg","vavB1vDFRBAFm4eM9iARcw==":"molinon%20habitacion%203-2000x1066.jpg","eSLjYslrXgoq1aSihl1cGw==":"molinon%20restaurante-2000x1066.jpg","4W+I18LCEWOgPZBI125YTw==":"pe%C3%B1agrande%20exterior-2000x1497.jpg","Ys6UcZuiE26LSAWbiN5FDg==":"pe%C3%B1agrande%20habitacion%201-2000x1314.jpg","7wGBUJMAV6MMy46sy04Vfg==":"pe%C3%B1agrande%20habitacion%202-2000x1321.jpg","o99U3q94RWshV6Tf+eKSrQ==":"pe%C3%B1agrande%20exterior%202-2000x1497.jpg","o7+zDWn7onYb3461idnQng==":"hotel%20ana%20entrada-2000x1328.jpg","BfmtNF1IMH3Co5svPGOtqQ==":"hotel%20ana%20habitacion%201-2000x1328.jpg","tP/A3v/RiRsEyCCuQ5kI7g==":"hotel%20ana%20habitacion%202-2000x1328.jpg","KVB3e6rE/PJtyBJXZqRBPA==":"leitariegos-2000x1120.jpg","bs0fIJzZPbuOA/mLHne5fw==":"leitariegos%20(1)-2000x1500.jpg","z2qRJCqv1TfGgDx0e2uwsg==":"leitariegos%202-2000x1498.jpg","ptnB5TKajgFbO0rzJCshUQ==":"leitariegos-1400x784.jpg","4KIphwhBtdqJr/GpsuJmpg==":"karts%20nuevos-2000x1333.jpg","K2nb1+0+0lXBhyAZXaPUuA==":"mezcla-2000x1119.jpg","UzQUrVguKl9daGJwqEEPtg==":"leitariegos-600x336.jpg","1yKE0lz30c7q1uRpyc3VkQ==":"karts%20nuevos-600x399.jpg","34e6jjein8boEIgPm/dhkA==":"cangas%20puente%202-600x801.jpg","eQ2KlJo/y3a/f6ek9khwFw==":"prada-600x450.jpg","sMZu5xpeTtOsy4hhgg3ubQ==":"corias-600x399.jpg","9MqQRu309Nht/ny+6HfpvA==":"prada-2000x1502.jpg","H3GFTq5J/mHtDUNZsHBUSw==":"prada-1400x1051.jpg","5R9kEZEeYY/lkhZSJxzL2A==":"logo_png_negro-128x128.png","MrBrw+8kgfxvwkG6z3oAFA==":"cangas%20puente%202-2000x2670.jpg","o04MFuvt9xE7YjOC1wQ55g==":"cangas%20puente%202-1400x1869.jpg","Tbef8grbYxwy76RhMTN/9g==":"corias-2000x1331.jpg","R0+uuV4Aa8j8UWPgj3apnA==":"corias-1400x931.jpg","qytfxaNSkFMdoQxkEeFY9w==":"mezcla02-2000x1122.jpg","7ElNyjDCTtpL1W2sq+mWdw==":"karts%20nuevos-1400x933.jpg","xYAT1IyMzDE58f5j9sJhaQ==":"corias%20desenfocada-2000x1330.jpg","UB8+1wgJzxDrnP3eF+sTYg==":"leitariegos-1-2000x1120.jpg"}